{
  "ID": "282cd1fa-cbd7-40eb-a886-5a44bec4ccc3",
  "Root": {
    "alive": true,
    "content": [
      "c2e36c7c-030c-48db-94f4-4b53d35ca45b",
      "3b8be8aa-ac63-4e9e-a5d6-062c5d697c5e",
      "2d4a165e-8814-4dc2-893f-f9a5b9b316fb",
      "a96f24a4-64fc-4e65-a763-1e5c007d88be"
    ],
    "created_by": "bb760e2d-d679-4b64-b2a9-03005b21870a",
    "created_time": 1493077477989,
    "id": "282cd1fa-cbd7-40eb-a886-5a44bec4ccc3",
    "last_edited_by": "bb760e2d-d679-4b64-b2a9-03005b21870a",
    "last_edited_time": 1529120456638,
    "parent_id": "e4fe2d9f-ae30-4e3a-beb9-b8316b9e2d62",
    "parent_table": "block",
    "properties": {
      "title": [
        [
          "valgrind"
        ]
      ]
    },
    "type": "page",
    "version": 3,
    "content_resolved": [
      {
        "alive": true,
        "created_by": "bb760e2d-d679-4b64-b2a9-03005b21870a",
        "created_time": 1512024101394,
        "id": "c2e36c7c-030c-48db-94f4-4b53d35ca45b",
        "last_edited_by": "bb760e2d-d679-4b64-b2a9-03005b21870a",
        "last_edited_time": 1512024101394,
        "parent_id": "282cd1fa-cbd7-40eb-a886-5a44bec4ccc3",
        "parent_table": "block",
        "properties": {
          "title": [
            [
              "Running with memleak detection:"
            ]
          ]
        },
        "type": "text",
        "version": 0,
        "inline_content": [
          {
            "Text": "Running with memleak detection:"
          }
        ]
      },
      {
        "alive": true,
        "created_by": "bb760e2d-d679-4b64-b2a9-03005b21870a",
        "created_time": 1512024111622,
        "id": "3b8be8aa-ac63-4e9e-a5d6-062c5d697c5e",
        "last_edited_by": "bb760e2d-d679-4b64-b2a9-03005b21870a",
        "last_edited_time": 1512024111622,
        "parent_id": "282cd1fa-cbd7-40eb-a886-5a44bec4ccc3",
        "parent_table": "block",
        "properties": {
          "title": [
            [
              "valgrind —tool=memcheck —leak-check=full —show-leak-kinds=all ./program",
              [
                [
                  "c"
                ]
              ]
            ],
            [
              " "
            ]
          ]
        },
        "type": "bulleted_list",
        "version": 0,
        "inline_content": [
          {
            "Text": "valgrind —tool=memcheck —leak-check=full —show-leak-kinds=all ./program",
            "AttrFlags": 2
          },
          {
            "Text": " "
          }
        ]
      },
      {
        "alive": true,
        "created_by": "bb760e2d-d679-4b64-b2a9-03005b21870a",
        "created_time": 1493077484545,
        "id": "2d4a165e-8814-4dc2-893f-f9a5b9b316fb",
        "last_edited_by": "bb760e2d-d679-4b64-b2a9-03005b21870a",
        "last_edited_time": 1493077484545,
        "parent_id": "282cd1fa-cbd7-40eb-a886-5a44bec4ccc3",
        "parent_table": "block",
        "properties": {
          "title": [
            [
              "Links:\n* "
            ],
            [
              "https://eklitzke.org/an-introduction-to-valgrind-memcheck",
              [
                [
                  "a",
                  "https://eklitzke.org/an-introduction-to-valgrind-memcheck"
                ]
              ]
            ]
          ]
        },
        "type": "text",
        "version": 0,
        "inline_content": [
          {
            "Text": "Links:\n* "
          },
          {
            "Text": "https://eklitzke.org/an-introduction-to-valgrind-memcheck",
            "Link": "https://eklitzke.org/an-introduction-to-valgrind-memcheck"
          }
        ]
      },
      {
        "alive": true,
        "created_by": "bb760e2d-d679-4b64-b2a9-03005b21870a",
        "created_time": 1493077488553,
        "id": "a96f24a4-64fc-4e65-a763-1e5c007d88be",
        "last_edited_by": "bb760e2d-d679-4b64-b2a9-03005b21870a",
        "last_edited_time": 1493077488553,
        "parent_id": "282cd1fa-cbd7-40eb-a886-5a44bec4ccc3",
        "parent_table": "block",
        "type": "text",
        "version": 0
      }
    ],
    "title": "valgrind"
  },
  "Users": [
    {
      "email": "kkowalczyk@gmail.com",
      "family_name": "Kowalczyk",
      "given_name": "Krzysztof",
      "id": "bb760e2d-d679-4b64-b2a9-03005b21870a",
      "locale": "en",
      "mobile_onboarding_completed": true,
      "onboarding_completed": true,
      "profile_photo": "https://s3-us-west-2.amazonaws.com/public.notion-static.com/2dcaa66c-7674-4ff6-9924-601785b63561/head-bw-640x960.png",
      "time_zone": "America/Los_Angeles",
      "version": 28
    }
  ],
  "Tables": null
}