{
  "ID": "4b2b3625-1643-4550-a06e-f5ad5056145d",
  "Page": {
    "alive": true,
    "content": [
      "7959f0f0-8fd8-4ad7-abca-83b315b6f794",
      "182ece8b-feb2-4848-b440-b395548de7e1",
      "be3516a0-b38d-4688-a622-55c5e7bebd4d",
      "2699957f-d024-4b5a-8fda-78d795f6d73a",
      "65c71590-931d-485e-8247-b95b28c61345"
    ],
    "created_by": "bb760e2d-d679-4b64-b2a9-03005b21870a",
    "created_time": 1530157297098,
    "format": {
      "page_full_width": true,
      "page_small_text": true
    },
    "id": "4b2b3625-1643-4550-a06e-f5ad5056145d",
    "ignore_block_count": true,
    "last_edited_by": "bb760e2d-d679-4b64-b2a9-03005b21870a",
    "last_edited_time": 1531383225679,
    "parent_id": "300db9dc-27c8-4958-a08b-8d0c37f4cfe5",
    "parent_table": "block",
    "properties": {
      "title": [
        [
          "The power of endorsement"
        ]
      ]
    },
    "type": "page",
    "version": 57,
    "content_resolved": [
      {
        "alive": true,
        "created_by": "bb760e2d-d679-4b64-b2a9-03005b21870a",
        "created_time": 1530157297097,
        "id": "7959f0f0-8fd8-4ad7-abca-83b315b6f794",
        "ignore_block_count": true,
        "last_edited_by": "bb760e2d-d679-4b64-b2a9-03005b21870a",
        "last_edited_time": 1531383225679,
        "parent_id": "4b2b3625-1643-4550-a06e-f5ad5056145d",
        "parent_table": "block",
        "properties": {
          "title": [
            [
              "Id: 1478"
            ]
          ]
        },
        "type": "text",
        "version": 7,
        "inline_content": [
          {
            "Text": "Id: 1478"
          }
        ]
      },
      {
        "alive": true,
        "created_by": "bb760e2d-d679-4b64-b2a9-03005b21870a",
        "created_time": 1531122548247,
        "id": "182ece8b-feb2-4848-b440-b395548de7e1",
        "last_edited_by": "bb760e2d-d679-4b64-b2a9-03005b21870a",
        "last_edited_time": 1531128383260,
        "parent_id": "4b2b3625-1643-4550-a06e-f5ad5056145d",
        "parent_table": "block",
        "properties": {
          "title": [
            [
              "Date: 2002-12-16T04:55:42-08:00"
            ]
          ]
        },
        "type": "text",
        "version": 12,
        "inline_content": [
          {
            "Text": "Date: 2002-12-16T04:55:42-08:00"
          }
        ]
      },
      {
        "alive": true,
        "created_by": "bb760e2d-d679-4b64-b2a9-03005b21870a",
        "created_time": 1531122552310,
        "id": "be3516a0-b38d-4688-a622-55c5e7bebd4d",
        "last_edited_by": "bb760e2d-d679-4b64-b2a9-03005b21870a",
        "last_edited_time": 1531122554479,
        "parent_id": "4b2b3625-1643-4550-a06e-f5ad5056145d",
        "parent_table": "block",
        "properties": {
          "title": [
            [
              "Status: notimportant"
            ]
          ]
        },
        "type": "text",
        "version": 10,
        "inline_content": [
          {
            "Text": "Status: notimportant"
          }
        ]
      },
      {
        "alive": true,
        "created_by": "bb760e2d-d679-4b64-b2a9-03005b21870a",
        "created_time": 1531122554479,
        "id": "2699957f-d024-4b5a-8fda-78d795f6d73a",
        "last_edited_by": "bb760e2d-d679-4b64-b2a9-03005b21870a",
        "last_edited_time": 1531383224454,
        "parent_id": "4b2b3625-1643-4550-a06e-f5ad5056145d",
        "parent_table": "block",
        "type": "text",
        "version": 12
      },
      {
        "alive": true,
        "created_by": "bb760e2d-d679-4b64-b2a9-03005b21870a",
        "created_time": 1531122557135,
        "id": "65c71590-931d-485e-8247-b95b28c61345",
        "last_edited_by": "bb760e2d-d679-4b64-b2a9-03005b21870a",
        "last_edited_time": 1531122557153,
        "parent_id": "4b2b3625-1643-4550-a06e-f5ad5056145d",
        "parent_table": "block",
        "properties": {
          "title": [
            [
              "Forums on "
            ],
            [
              "Joel On Software",
              [
                [
                  "a",
                  "http://www.joelonsoftware.com/"
                ]
              ]
            ],
            [
              " are interesting on average but some posts are much more interesting than others, like "
            ],
            [
              "this one",
              [
                [
                  "a",
                  "http://discuss.fogcreek.com/joelonsoftware/default.asp?cmd=show\u0026ixPost=22534\u0026ixReplies=14"
                ]
              ]
            ],
            [
              " on the power of endorsements."
            ]
          ]
        },
        "type": "text",
        "version": 6,
        "inline_content": [
          {
            "Text": "Forums on "
          },
          {
            "Text": "Joel On Software",
            "Link": "http://www.joelonsoftware.com/"
          },
          {
            "Text": " are interesting on average but some posts are much more interesting than others, like "
          },
          {
            "Text": "this one",
            "Link": "http://discuss.fogcreek.com/joelonsoftware/default.asp?cmd=show\u0026ixPost=22534\u0026ixReplies=14"
          },
          {
            "Text": " on the power of endorsements."
          }
        ]
      }
    ],
    "title": "The power of endorsement",
    "format_page": {
      "page_cover": "",
      "page_cover_position": 0,
      "page_font": "",
      "page_full_width": true,
      "page_icon": "",
      "page_small_text": true
    }
  },
  "Users": [
    {
      "email": "kkowalczyk@gmail.com",
      "family_name": "Kowalczyk",
      "given_name": "Krzysztof",
      "id": "bb760e2d-d679-4b64-b2a9-03005b21870a",
      "locale": "en",
      "mobile_onboarding_completed": true,
      "onboarding_completed": true,
      "profile_photo": "https://s3-us-west-2.amazonaws.com/public.notion-static.com/2dcaa66c-7674-4ff6-9924-601785b63561/head-bw-640x960.png",
      "time_zone": "America/Los_Angeles",
      "version": 9
    }
  ],
  "Collections": null,
  "CollectionViews": null
}