{
  "ID": "aad8cfc1-84b0-4181-8ffe-6fabf2fada34",
  "Root": {
    "alive": true,
    "content": [
      "adc214d4-46e6-4d50-8038-5dcbd3028ddd"
    ],
    "created_by": "bb760e2d-d679-4b64-b2a9-03005b21870a",
    "created_time": 1533091350009,
    "format": {
      "page_font": "mono",
      "page_full_width": true,
      "page_small_text": true
    },
    "id": "aad8cfc1-84b0-4181-8ffe-6fabf2fada34",
    "last_edited_by": "bb760e2d-d679-4b64-b2a9-03005b21870a",
    "last_edited_time": 1533091367432,
    "parent_id": "46aa7c6d-0833-42bb-b35f-7a7de0a994c0",
    "parent_table": "block",
    "properties": {
      "title": [
        [
          "devlog 2018-08"
        ]
      ]
    },
    "type": "page",
    "version": 51,
    "content_resolved": [
      {
        "alive": true,
        "created_by": "bb760e2d-d679-4b64-b2a9-03005b21870a",
        "created_time": 1533091355662,
        "id": "adc214d4-46e6-4d50-8038-5dcbd3028ddd",
        "last_edited_by": "bb760e2d-d679-4b64-b2a9-03005b21870a",
        "last_edited_time": 1533091355677,
        "parent_id": "aad8cfc1-84b0-4181-8ffe-6fabf2fada34",
        "parent_table": "block",
        "type": "text",
        "version": 6
      }
    ],
    "title": "devlog 2018-08",
    "format_page": {
      "page_cover": "",
      "page_cover_position": 0,
      "page_font": "mono",
      "page_full_width": true,
      "page_icon": "",
      "page_small_text": true
    }
  },
  "Users": [
    {
      "email": "kkowalczyk@gmail.com",
      "family_name": "Kowalczyk",
      "given_name": "Krzysztof",
      "id": "bb760e2d-d679-4b64-b2a9-03005b21870a",
      "locale": "en",
      "mobile_onboarding_completed": true,
      "onboarding_completed": true,
      "profile_photo": "https://s3-us-west-2.amazonaws.com/public.notion-static.com/2dcaa66c-7674-4ff6-9924-601785b63561/head-bw-640x960.png",
      "time_zone": "America/Los_Angeles",
      "version": 10
    }
  ],
  "Tables": null
}