{
  "ID": "bee99cd6-acaf-4820-8ed2-6bf0d3c20284",
  "Page": {
    "alive": true,
    "content": [
      "fd035cb5-ab7b-4220-a606-94162c956519",
      "17ddbdf8-7eda-4857-8049-d2f3766dd234",
      "67c0ef5f-ef6c-4a84-9dfc-3d285f2b9e2f",
      "95f7469e-d115-4a3a-9910-f8d14eff9493",
      "a843fbfb-36e7-4044-bf52-bf0840ef93b5"
    ],
    "created_by": "bb760e2d-d679-4b64-b2a9-03005b21870a",
    "created_time": 1530157267210,
    "format": {
      "page_full_width": true,
      "page_small_text": true
    },
    "id": "bee99cd6-acaf-4820-8ed2-6bf0d3c20284",
    "ignore_block_count": true,
    "last_edited_by": "bb760e2d-d679-4b64-b2a9-03005b21870a",
    "last_edited_time": 1531382010749,
    "parent_id": "300db9dc-27c8-4958-a08b-8d0c37f4cfe5",
    "parent_table": "block",
    "properties": {
      "title": [
        [
          "Life of Hellen Keller"
        ]
      ]
    },
    "type": "page",
    "version": 57,
    "content_resolved": [
      {
        "alive": true,
        "created_by": "bb760e2d-d679-4b64-b2a9-03005b21870a",
        "created_time": 1530157267207,
        "id": "fd035cb5-ab7b-4220-a606-94162c956519",
        "ignore_block_count": true,
        "last_edited_by": "bb760e2d-d679-4b64-b2a9-03005b21870a",
        "last_edited_time": 1531382010749,
        "parent_id": "bee99cd6-acaf-4820-8ed2-6bf0d3c20284",
        "parent_table": "block",
        "properties": {
          "title": [
            [
              "Id: 1363"
            ]
          ]
        },
        "type": "text",
        "version": 7,
        "inline_content": [
          {
            "Text": "Id: 1363"
          }
        ]
      },
      {
        "alive": true,
        "created_by": "bb760e2d-d679-4b64-b2a9-03005b21870a",
        "created_time": 1531120613187,
        "id": "17ddbdf8-7eda-4857-8049-d2f3766dd234",
        "last_edited_by": "bb760e2d-d679-4b64-b2a9-03005b21870a",
        "last_edited_time": 1531128097429,
        "parent_id": "bee99cd6-acaf-4820-8ed2-6bf0d3c20284",
        "parent_table": "block",
        "properties": {
          "title": [
            [
              "Date: 2002-08-04T00:00:06-07:00"
            ]
          ]
        },
        "type": "text",
        "version": 12,
        "inline_content": [
          {
            "Text": "Date: 2002-08-04T00:00:06-07:00"
          }
        ]
      },
      {
        "alive": true,
        "created_by": "bb760e2d-d679-4b64-b2a9-03005b21870a",
        "created_time": 1531120618708,
        "id": "67c0ef5f-ef6c-4a84-9dfc-3d285f2b9e2f",
        "last_edited_by": "bb760e2d-d679-4b64-b2a9-03005b21870a",
        "last_edited_time": 1531120620572,
        "parent_id": "bee99cd6-acaf-4820-8ed2-6bf0d3c20284",
        "parent_table": "block",
        "properties": {
          "title": [
            [
              "Status: hidden"
            ]
          ]
        },
        "type": "text",
        "version": 10,
        "inline_content": [
          {
            "Text": "Status: hidden"
          }
        ]
      },
      {
        "alive": true,
        "created_by": "bb760e2d-d679-4b64-b2a9-03005b21870a",
        "created_time": 1531120620572,
        "id": "95f7469e-d115-4a3a-9910-f8d14eff9493",
        "last_edited_by": "bb760e2d-d679-4b64-b2a9-03005b21870a",
        "last_edited_time": 1531382009334,
        "parent_id": "bee99cd6-acaf-4820-8ed2-6bf0d3c20284",
        "parent_table": "block",
        "type": "text",
        "version": 12
      },
      {
        "alive": true,
        "created_by": "bb760e2d-d679-4b64-b2a9-03005b21870a",
        "created_time": 1531120624028,
        "id": "a843fbfb-36e7-4044-bf52-bf0840ef93b5",
        "last_edited_by": "bb760e2d-d679-4b64-b2a9-03005b21870a",
        "last_edited_time": 1531120624043,
        "parent_id": "bee99cd6-acaf-4820-8ed2-6bf0d3c20284",
        "parent_table": "block",
        "properties": {
          "title": [
            [
              "Life of Hellen Keller",
              [
                [
                  "a",
                  "http://www.afb.org/info_document_view.asp?documentid=1351"
                ]
              ]
            ],
            [
              ". Simply amazing."
            ]
          ]
        },
        "type": "text",
        "version": 6,
        "inline_content": [
          {
            "Text": "Life of Hellen Keller",
            "Link": "http://www.afb.org/info_document_view.asp?documentid=1351"
          },
          {
            "Text": ". Simply amazing."
          }
        ]
      }
    ],
    "title": "Life of Hellen Keller",
    "format_page": {
      "page_cover": "",
      "page_cover_position": 0,
      "page_font": "",
      "page_full_width": true,
      "page_icon": "",
      "page_small_text": true
    }
  },
  "Users": [
    {
      "email": "kkowalczyk@gmail.com",
      "family_name": "Kowalczyk",
      "given_name": "Krzysztof",
      "id": "bb760e2d-d679-4b64-b2a9-03005b21870a",
      "locale": "en",
      "mobile_onboarding_completed": true,
      "onboarding_completed": true,
      "profile_photo": "https://s3-us-west-2.amazonaws.com/public.notion-static.com/2dcaa66c-7674-4ff6-9924-601785b63561/head-bw-640x960.png",
      "time_zone": "America/Los_Angeles",
      "version": 9
    }
  ],
  "Collections": null,
  "CollectionViews": null
}