{
  "ID": "d2061080-04d4-4583-ac50-744749666286",
  "Page": {
    "alive": true,
    "content": [
      "edf18621-33d5-4f0e-906b-82d1db026058",
      "aba9724c-0930-41d0-aaa1-7137049bb57e",
      "3ec5d393-4233-4715-b5cf-024a1a9f57eb",
      "fb0558af-df41-4504-a90c-b2a9ae5f0cc3",
      "1ba74d17-c630-4b0a-b118-f895dbbab51f",
      "79148cf0-170a-48ac-8f53-c02283469d46",
      "84525f3e-6981-447c-a93d-a090d2d6559e",
      "faabdf3c-019b-42cc-b4cf-8d81c75da28d",
      "017cec8d-97aa-4175-9644-ff24ec8d54b6"
    ],
    "created_by": "bb760e2d-d679-4b64-b2a9-03005b21870a",
    "created_time": 1530157283279,
    "format": {
      "page_full_width": true,
      "page_small_text": true
    },
    "id": "d2061080-04d4-4583-ac50-744749666286",
    "ignore_block_count": true,
    "last_edited_by": "bb760e2d-d679-4b64-b2a9-03005b21870a",
    "last_edited_time": 1531382999280,
    "parent_id": "300db9dc-27c8-4958-a08b-8d0c37f4cfe5",
    "parent_table": "block",
    "properties": {
      "title": [
        [
          "You’ll have a job"
        ]
      ]
    },
    "type": "page",
    "version": 55,
    "content_resolved": [
      {
        "alive": true,
        "created_by": "bb760e2d-d679-4b64-b2a9-03005b21870a",
        "created_time": 1530157283276,
        "id": "edf18621-33d5-4f0e-906b-82d1db026058",
        "ignore_block_count": true,
        "last_edited_by": "bb760e2d-d679-4b64-b2a9-03005b21870a",
        "last_edited_time": 1531382996056,
        "parent_id": "d2061080-04d4-4583-ac50-744749666286",
        "parent_table": "block",
        "properties": {
          "title": [
            [
              "Id: 1418"
            ]
          ]
        },
        "type": "text",
        "version": 7,
        "inline_content": [
          {
            "Text": "Id: 1418"
          }
        ]
      },
      {
        "alive": true,
        "created_by": "bb760e2d-d679-4b64-b2a9-03005b21870a",
        "created_time": 1531121656416,
        "id": "aba9724c-0930-41d0-aaa1-7137049bb57e",
        "last_edited_by": "bb760e2d-d679-4b64-b2a9-03005b21870a",
        "last_edited_time": 1531128256121,
        "parent_id": "d2061080-04d4-4583-ac50-744749666286",
        "parent_table": "block",
        "properties": {
          "title": [
            [
              "Date: 2002-09-17T09:14:55-07:00"
            ]
          ]
        },
        "type": "text",
        "version": 12,
        "inline_content": [
          {
            "Text": "Date: 2002-09-17T09:14:55-07:00"
          }
        ]
      },
      {
        "alive": true,
        "created_by": "bb760e2d-d679-4b64-b2a9-03005b21870a",
        "created_time": 1531121660983,
        "id": "3ec5d393-4233-4715-b5cf-024a1a9f57eb",
        "last_edited_by": "bb760e2d-d679-4b64-b2a9-03005b21870a",
        "last_edited_time": 1531382994695,
        "parent_id": "d2061080-04d4-4583-ac50-744749666286",
        "parent_table": "block",
        "type": "text",
        "version": 12
      },
      {
        "alive": true,
        "created_by": "bb760e2d-d679-4b64-b2a9-03005b21870a",
        "created_time": 1531121663254,
        "id": "fb0558af-df41-4504-a90c-b2a9ae5f0cc3",
        "last_edited_by": "bb760e2d-d679-4b64-b2a9-03005b21870a",
        "last_edited_time": 1531121663268,
        "parent_id": "d2061080-04d4-4583-ac50-744749666286",
        "parent_table": "block",
        "properties": {
          "title": [
            [
              "It comes from the “I couldn’t say it better myself” department: this "
            ],
            [
              "excellent post",
              [
                [
                  "a",
                  "http://discuss.fogcreek.com/joelonsoftware/default.asp?cmd=show\u0026ixPost=15621\u0026ixReplies=8"
                ]
              ]
            ],
            [
              " presents 12 reasons why a good programmer should not worry about employment."
            ]
          ]
        },
        "type": "text",
        "version": 6,
        "inline_content": [
          {
            "Text": "It comes from the “I couldn’t say it better myself” department: this "
          },
          {
            "Text": "excellent post",
            "Link": "http://discuss.fogcreek.com/joelonsoftware/default.asp?cmd=show\u0026ixPost=15621\u0026ixReplies=8"
          },
          {
            "Text": " presents 12 reasons why a good programmer should not worry about employment."
          }
        ]
      },
      {
        "alive": true,
        "created_by": "bb760e2d-d679-4b64-b2a9-03005b21870a",
        "created_time": 1530157283277,
        "id": "1ba74d17-c630-4b0a-b118-f895dbbab51f",
        "ignore_block_count": true,
        "last_edited_by": "bb760e2d-d679-4b64-b2a9-03005b21870a",
        "last_edited_time": 1530157283277,
        "parent_id": "d2061080-04d4-4583-ac50-744749666286",
        "parent_table": "block",
        "properties": {
          "title": [
            [
              "I remember discussion with other programmers where they claimed that because VB and other such tools make programming easier, there will be less work and less demand for programmers."
            ]
          ]
        },
        "type": "text",
        "version": 1,
        "inline_content": [
          {
            "Text": "I remember discussion with other programmers where they claimed that because VB and other such tools make programming easier, there will be less work and less demand for programmers."
          }
        ]
      },
      {
        "alive": true,
        "created_by": "bb760e2d-d679-4b64-b2a9-03005b21870a",
        "created_time": 1530157283277,
        "id": "79148cf0-170a-48ac-8f53-c02283469d46",
        "ignore_block_count": true,
        "last_edited_by": "bb760e2d-d679-4b64-b2a9-03005b21870a",
        "last_edited_time": 1530157283277,
        "parent_id": "d2061080-04d4-4583-ac50-744749666286",
        "parent_table": "block",
        "properties": {
          "title": [
            [
              "To which I say: bull."
            ]
          ]
        },
        "type": "text",
        "version": 1,
        "inline_content": [
          {
            "Text": "To which I say: bull."
          }
        ]
      },
      {
        "alive": true,
        "created_by": "bb760e2d-d679-4b64-b2a9-03005b21870a",
        "created_time": 1530157283278,
        "id": "84525f3e-6981-447c-a93d-a090d2d6559e",
        "ignore_block_count": true,
        "last_edited_by": "bb760e2d-d679-4b64-b2a9-03005b21870a",
        "last_edited_time": 1530157283278,
        "parent_id": "d2061080-04d4-4583-ac50-744749666286",
        "parent_table": "block",
        "properties": {
          "title": [
            [
              "Those tools make "
            ],
            [
              "some",
              [
                [
                  "i"
                ]
              ]
            ],
            [
              " programming easier but at the same time a lot of programming becomes harder because our software gets bigger."
            ]
          ]
        },
        "type": "text",
        "version": 1,
        "inline_content": [
          {
            "Text": "Those tools make "
          },
          {
            "Text": "some",
            "AttrFlags": 4
          },
          {
            "Text": " programming easier but at the same time a lot of programming becomes harder because our software gets bigger."
          }
        ]
      },
      {
        "alive": true,
        "created_by": "bb760e2d-d679-4b64-b2a9-03005b21870a",
        "created_time": 1530157283278,
        "id": "faabdf3c-019b-42cc-b4cf-8d81c75da28d",
        "ignore_block_count": true,
        "last_edited_by": "bb760e2d-d679-4b64-b2a9-03005b21870a",
        "last_edited_time": 1530157283278,
        "parent_id": "d2061080-04d4-4583-ac50-744749666286",
        "parent_table": "block",
        "properties": {
          "title": [
            [
              "We need to keep existing software up-to-date and every year we come up with completely new categories of software to write: web servers, IM systems, weblog software, native XML databases, web search engines."
            ]
          ]
        },
        "type": "text",
        "version": 1,
        "inline_content": [
          {
            "Text": "We need to keep existing software up-to-date and every year we come up with completely new categories of software to write: web servers, IM systems, weblog software, native XML databases, web search engines."
          }
        ]
      },
      {
        "alive": true,
        "created_by": "bb760e2d-d679-4b64-b2a9-03005b21870a",
        "created_time": 1530157283278,
        "id": "017cec8d-97aa-4175-9644-ff24ec8d54b6",
        "ignore_block_count": true,
        "last_edited_by": "bb760e2d-d679-4b64-b2a9-03005b21870a",
        "last_edited_time": 1530157283278,
        "parent_id": "d2061080-04d4-4583-ac50-744749666286",
        "parent_table": "block",
        "properties": {
          "title": [
            [
              "There’ll be plenty of work for competent programmers."
            ]
          ]
        },
        "type": "text",
        "version": 1,
        "inline_content": [
          {
            "Text": "There’ll be plenty of work for competent programmers."
          }
        ]
      }
    ],
    "title": "You’ll have a job",
    "format_page": {
      "page_cover": "",
      "page_cover_position": 0,
      "page_font": "",
      "page_full_width": true,
      "page_icon": "",
      "page_small_text": true
    }
  },
  "Users": [
    {
      "email": "kkowalczyk@gmail.com",
      "family_name": "Kowalczyk",
      "given_name": "Krzysztof",
      "id": "bb760e2d-d679-4b64-b2a9-03005b21870a",
      "locale": "en",
      "mobile_onboarding_completed": true,
      "onboarding_completed": true,
      "profile_photo": "https://s3-us-west-2.amazonaws.com/public.notion-static.com/2dcaa66c-7674-4ff6-9924-601785b63561/head-bw-640x960.png",
      "time_zone": "America/Los_Angeles",
      "version": 9
    }
  ],
  "Collections": null,
  "CollectionViews": null
}