{
  "ID": "d78b93f7-81d3-4530-b2b0-29d7756c05ca",
  "Page": {
    "alive": true,
    "content": [
      "5fa17697-f734-4bcf-8e94-1a83e557a2ac",
      "116beaeb-ed4e-45e9-9f25-86770d24e3d1",
      "94a66bde-89aa-4fa9-b9f5-66d09f60adc1",
      "b10880b1-348e-4041-a6e7-502e173c8a2e",
      "6b051d07-e4ed-46bc-8ae3-8aa5a6f15f3c",
      "a707cc85-f3da-4f60-be27-11fc82d9815b"
    ],
    "created_by": "bb760e2d-d679-4b64-b2a9-03005b21870a",
    "created_time": 1531202574988,
    "format": {
      "page_full_width": true,
      "page_small_text": true
    },
    "id": "d78b93f7-81d3-4530-b2b0-29d7756c05ca",
    "last_edited_by": "bb760e2d-d679-4b64-b2a9-03005b21870a",
    "last_edited_time": 1531622722665,
    "parent_id": "300db9dc-27c8-4958-a08b-8d0c37f4cfe5",
    "parent_table": "block",
    "properties": {
      "title": [
        [
          "Websites with free ePub and mobi ebooks"
        ]
      ]
    },
    "type": "page",
    "version": 7,
    "content_resolved": [
      {
        "alive": true,
        "created_by": "bb760e2d-d679-4b64-b2a9-03005b21870a",
        "created_time": 1531202574988,
        "id": "5fa17697-f734-4bcf-8e94-1a83e557a2ac",
        "last_edited_by": "bb760e2d-d679-4b64-b2a9-03005b21870a",
        "last_edited_time": 1531622722665,
        "parent_id": "d78b93f7-81d3-4530-b2b0-29d7756c05ca",
        "parent_table": "block",
        "properties": {
          "title": [
            [
              "Id: 1103001"
            ]
          ]
        },
        "type": "text",
        "version": 3,
        "inline_content": [
          {
            "Text": "Id: 1103001"
          }
        ]
      },
      {
        "alive": true,
        "created_by": "bb760e2d-d679-4b64-b2a9-03005b21870a",
        "created_time": 1531202574988,
        "id": "116beaeb-ed4e-45e9-9f25-86770d24e3d1",
        "last_edited_by": "bb760e2d-d679-4b64-b2a9-03005b21870a",
        "last_edited_time": 1531202574988,
        "parent_id": "d78b93f7-81d3-4530-b2b0-29d7756c05ca",
        "parent_table": "block",
        "properties": {
          "title": [
            [
              "Tags: sumatra"
            ]
          ]
        },
        "type": "text",
        "version": 1,
        "inline_content": [
          {
            "Text": "Tags: sumatra"
          }
        ]
      },
      {
        "alive": true,
        "created_by": "bb760e2d-d679-4b64-b2a9-03005b21870a",
        "created_time": 1531202574988,
        "id": "94a66bde-89aa-4fa9-b9f5-66d09f60adc1",
        "last_edited_by": "bb760e2d-d679-4b64-b2a9-03005b21870a",
        "last_edited_time": 1531202574988,
        "parent_id": "d78b93f7-81d3-4530-b2b0-29d7756c05ca",
        "parent_table": "block",
        "properties": {
          "title": [
            [
              "Date: 2012-05-04T15:58:27-07:00"
            ]
          ]
        },
        "type": "text",
        "version": 1,
        "inline_content": [
          {
            "Text": "Date: 2012-05-04T15:58:27-07:00"
          }
        ]
      },
      {
        "alive": true,
        "created_by": "bb760e2d-d679-4b64-b2a9-03005b21870a",
        "created_time": 1531202574989,
        "id": "b10880b1-348e-4041-a6e7-502e173c8a2e",
        "last_edited_by": "bb760e2d-d679-4b64-b2a9-03005b21870a",
        "last_edited_time": 1531622720295,
        "parent_id": "d78b93f7-81d3-4530-b2b0-29d7756c05ca",
        "parent_table": "block",
        "type": "text",
        "version": 3
      },
      {
        "alive": true,
        "created_by": "bb760e2d-d679-4b64-b2a9-03005b21870a",
        "created_time": 1531202574989,
        "id": "6b051d07-e4ed-46bc-8ae3-8aa5a6f15f3c",
        "last_edited_by": "bb760e2d-d679-4b64-b2a9-03005b21870a",
        "last_edited_time": 1531202574989,
        "parent_id": "d78b93f7-81d3-4530-b2b0-29d7756c05ca",
        "parent_table": "block",
        "properties": {
          "title": [
            [
              "Since "
            ],
            [
              "Sumatra",
              [
                [
                  "a",
                  "https://www.sumatrapdfreader.org/free-pdf-reader.html"
                ]
              ]
            ],
            [
              " now supports 2 most popular eBook formats (ePub and mobi), I’ve started collecting a list of websites that offer "
            ],
            [
              "free ePub and mobi eBooks",
              [
                [
                  "a",
                  "/articles/where-to-get-free-ebooks-epub-mobi.html"
                ]
              ]
            ],
            [
              "."
            ]
          ]
        },
        "type": "text",
        "version": 1,
        "inline_content": [
          {
            "Text": "Since "
          },
          {
            "Text": "Sumatra",
            "Link": "https://www.sumatrapdfreader.org/free-pdf-reader.html"
          },
          {
            "Text": " now supports 2 most popular eBook formats (ePub and mobi), I’ve started collecting a list of websites that offer "
          },
          {
            "Text": "free ePub and mobi eBooks",
            "Link": "/articles/where-to-get-free-ebooks-epub-mobi.html"
          },
          {
            "Text": "."
          }
        ]
      },
      {
        "alive": true,
        "created_by": "bb760e2d-d679-4b64-b2a9-03005b21870a",
        "created_time": 1531202574989,
        "id": "a707cc85-f3da-4f60-be27-11fc82d9815b",
        "last_edited_by": "bb760e2d-d679-4b64-b2a9-03005b21870a",
        "last_edited_time": 1531202574989,
        "parent_id": "d78b93f7-81d3-4530-b2b0-29d7756c05ca",
        "parent_table": "block",
        "type": "text",
        "version": 1
      }
    ],
    "title": "Websites with free ePub and mobi ebooks",
    "format_page": {
      "page_cover": "",
      "page_cover_position": 0,
      "page_font": "",
      "page_full_width": true,
      "page_icon": "",
      "page_small_text": true
    }
  },
  "Users": [
    {
      "email": "kkowalczyk@gmail.com",
      "family_name": "Kowalczyk",
      "given_name": "Krzysztof",
      "id": "bb760e2d-d679-4b64-b2a9-03005b21870a",
      "locale": "en",
      "mobile_onboarding_completed": true,
      "onboarding_completed": true,
      "profile_photo": "https://s3-us-west-2.amazonaws.com/public.notion-static.com/2dcaa66c-7674-4ff6-9924-601785b63561/head-bw-640x960.png",
      "time_zone": "America/Los_Angeles",
      "version": 9
    }
  ],
  "Collections": null,
  "CollectionViews": null
}