{
  "ID": "e7eb256f-bcbb-4034-a685-c46149832cd3",
  "Page": {
    "alive": true,
    "content": [
      "7fd59251-dd47-4a63-a3a5-4cc70aa09c51",
      "718c6517-ec1c-4665-80f5-8911a368908f",
      "c0827211-179c-49df-8dbb-e4f5b22fb124",
      "04498382-0935-48de-a539-d8d6ee4639e8",
      "f6d47cca-dfac-4f71-a1d6-a8003969bbc8",
      "11641ce4-385c-4156-96ed-4a3ebfc38f4d"
    ],
    "created_by": "bb760e2d-d679-4b64-b2a9-03005b21870a",
    "created_time": 1531195845656,
    "format": {
      "page_full_width": true,
      "page_small_text": true
    },
    "id": "e7eb256f-bcbb-4034-a685-c46149832cd3",
    "last_edited_by": "bb760e2d-d679-4b64-b2a9-03005b21870a",
    "last_edited_time": 1531624050797,
    "parent_id": "300db9dc-27c8-4958-a08b-8d0c37f4cfe5",
    "parent_table": "block",
    "properties": {
      "title": [
        [
          "Digg and the craft of catchy headlines"
        ]
      ]
    },
    "type": "page",
    "version": 11,
    "content_resolved": [
      {
        "alive": true,
        "created_by": "bb760e2d-d679-4b64-b2a9-03005b21870a",
        "created_time": 1531195845656,
        "id": "7fd59251-dd47-4a63-a3a5-4cc70aa09c51",
        "last_edited_by": "bb760e2d-d679-4b64-b2a9-03005b21870a",
        "last_edited_time": 1531624050797,
        "parent_id": "e7eb256f-bcbb-4034-a685-c46149832cd3",
        "parent_table": "block",
        "properties": {
          "title": [
            [
              "Id: 1943"
            ]
          ]
        },
        "type": "text",
        "version": 3,
        "inline_content": [
          {
            "Text": "Id: 1943"
          }
        ]
      },
      {
        "alive": true,
        "created_by": "bb760e2d-d679-4b64-b2a9-03005b21870a",
        "created_time": 1531195845656,
        "id": "718c6517-ec1c-4665-80f5-8911a368908f",
        "last_edited_by": "bb760e2d-d679-4b64-b2a9-03005b21870a",
        "last_edited_time": 1531195845656,
        "parent_id": "e7eb256f-bcbb-4034-a685-c46149832cd3",
        "parent_table": "block",
        "properties": {
          "title": [
            [
              "Date: 2006-03-11T15:07:34-08:00"
            ]
          ]
        },
        "type": "text",
        "version": 1,
        "inline_content": [
          {
            "Text": "Date: 2006-03-11T15:07:34-08:00"
          }
        ]
      },
      {
        "alive": true,
        "created_by": "bb760e2d-d679-4b64-b2a9-03005b21870a",
        "created_time": 1531195845656,
        "id": "c0827211-179c-49df-8dbb-e4f5b22fb124",
        "last_edited_by": "bb760e2d-d679-4b64-b2a9-03005b21870a",
        "last_edited_time": 1531624049754,
        "parent_id": "e7eb256f-bcbb-4034-a685-c46149832cd3",
        "parent_table": "block",
        "type": "text",
        "version": 3
      },
      {
        "alive": true,
        "created_by": "bb760e2d-d679-4b64-b2a9-03005b21870a",
        "created_time": 1531195845656,
        "id": "04498382-0935-48de-a539-d8d6ee4639e8",
        "last_edited_by": "bb760e2d-d679-4b64-b2a9-03005b21870a",
        "last_edited_time": 1531195845656,
        "parent_id": "e7eb256f-bcbb-4034-a685-c46149832cd3",
        "parent_table": "block",
        "properties": {
          "title": [
            [
              "Having used Digg for a while, it seems to me that there’s a growing appetite for crafting the headlines in a way that attracts the attention the most."
            ]
          ]
        },
        "type": "text",
        "version": 1,
        "inline_content": [
          {
            "Text": "Having used Digg for a while, it seems to me that there’s a growing appetite for crafting the headlines in a way that attracts the attention the most."
          }
        ]
      },
      {
        "alive": true,
        "created_by": "bb760e2d-d679-4b64-b2a9-03005b21870a",
        "created_time": 1531195845656,
        "id": "f6d47cca-dfac-4f71-a1d6-a8003969bbc8",
        "last_edited_by": "bb760e2d-d679-4b64-b2a9-03005b21870a",
        "last_edited_time": 1531195845656,
        "parent_id": "e7eb256f-bcbb-4034-a685-c46149832cd3",
        "parent_table": "block",
        "properties": {
          "title": [
            [
              "Those two examples from today’s list propelled me to make that observation:\n- "
            ],
            [
              "Former Google Employee says don’t buy Google stock",
              [
                [
                  "i"
                ]
              ]
            ],
            [
              ". Given the exoribitant price of Google stock, that’s a very rational advice. But the headline makes it seem like it means more than it does (as if ex-googler has any special insight into Google’s stock price).\n- "
            ],
            [
              "Motorola stock stumbles over 2 percent",
              [
                [
                  "i"
                ]
              ]
            ],
            [
              " (in reference to problems with Razr phones). A great stumble indeed.\nWhich is understandable: the point of posting an article is to have it digged by as many people as possible so that it appears on the main page. A catchy headline helps in that (since very few people bother to actually read the article and ponder its worthiness) so people try to create catchy headlines. Nothing new, really (we see that in newspapers, we see that in blogs) but still sad."
            ]
          ]
        },
        "type": "text",
        "version": 1,
        "inline_content": [
          {
            "Text": "Those two examples from today’s list propelled me to make that observation:\n- "
          },
          {
            "Text": "Former Google Employee says don’t buy Google stock",
            "AttrFlags": 4
          },
          {
            "Text": ". Given the exoribitant price of Google stock, that’s a very rational advice. But the headline makes it seem like it means more than it does (as if ex-googler has any special insight into Google’s stock price).\n- "
          },
          {
            "Text": "Motorola stock stumbles over 2 percent",
            "AttrFlags": 4
          },
          {
            "Text": " (in reference to problems with Razr phones). A great stumble indeed.\nWhich is understandable: the point of posting an article is to have it digged by as many people as possible so that it appears on the main page. A catchy headline helps in that (since very few people bother to actually read the article and ponder its worthiness) so people try to create catchy headlines. Nothing new, really (we see that in newspapers, we see that in blogs) but still sad."
          }
        ]
      },
      {
        "alive": true,
        "created_by": "bb760e2d-d679-4b64-b2a9-03005b21870a",
        "created_time": 1531195845656,
        "id": "11641ce4-385c-4156-96ed-4a3ebfc38f4d",
        "last_edited_by": "bb760e2d-d679-4b64-b2a9-03005b21870a",
        "last_edited_time": 1531195845656,
        "parent_id": "e7eb256f-bcbb-4034-a685-c46149832cd3",
        "parent_table": "block",
        "properties": {
          "title": [
            [
              "Says he who’s been guilty of that in the past and will be guilty of that in the future. Which brings me to "
            ],
            [
              "When the Anti-Choice Choose",
              [
                [
                  "a",
                  "http://mypage.direct.ca/w/writer/anti-tales.html"
                ]
              ]
            ],
            [
              " as a great example of how good humans are at self-deception and condemning activities they themselves engage in from time to time."
            ]
          ]
        },
        "type": "text",
        "version": 1,
        "inline_content": [
          {
            "Text": "Says he who’s been guilty of that in the past and will be guilty of that in the future. Which brings me to "
          },
          {
            "Text": "When the Anti-Choice Choose",
            "Link": "http://mypage.direct.ca/w/writer/anti-tales.html"
          },
          {
            "Text": " as a great example of how good humans are at self-deception and condemning activities they themselves engage in from time to time."
          }
        ]
      }
    ],
    "title": "Digg and the craft of catchy headlines",
    "format_page": {
      "page_cover": "",
      "page_cover_position": 0,
      "page_font": "",
      "page_full_width": true,
      "page_icon": "",
      "page_small_text": true
    }
  },
  "Users": [
    {
      "email": "kkowalczyk@gmail.com",
      "family_name": "Kowalczyk",
      "given_name": "Krzysztof",
      "id": "bb760e2d-d679-4b64-b2a9-03005b21870a",
      "locale": "en",
      "mobile_onboarding_completed": true,
      "onboarding_completed": true,
      "profile_photo": "https://s3-us-west-2.amazonaws.com/public.notion-static.com/2dcaa66c-7674-4ff6-9924-601785b63561/head-bw-640x960.png",
      "time_zone": "America/Los_Angeles",
      "version": 9
    }
  ],
  "Collections": null,
  "CollectionViews": null
}