{
  "ID": "f1fcdd01-b2dd-4794-a7af-3b00eebda21e",
  "Page": {
    "alive": true,
    "content": [
      "97ebb1ab-bfaa-4913-98a9-af4b830ea526",
      "bd8b7b4c-889e-4c57-b73d-c2af98fbbe49",
      "3eab842d-cc91-45d2-b15d-22ef10fc1055",
      "625c28fa-f561-469a-a625-a1fd501645ea",
      "d5b40c05-1d1d-411f-b01b-392542ba6783",
      "98afe68a-0b3a-4461-8a71-e29baa8c6ddc",
      "f7e8773f-7326-4401-9319-a36254b3f6a6",
      "807671d0-5d4a-48a3-b0be-af7b98567f28",
      "525f436a-17cf-4740-9dd9-b1c1f53f584b"
    ],
    "created_by": "bb760e2d-d679-4b64-b2a9-03005b21870a",
    "created_time": 1531736996053,
    "format": {
      "page_full_width": true,
      "page_small_text": true
    },
    "id": "f1fcdd01-b2dd-4794-a7af-3b00eebda21e",
    "last_edited_by": "bb760e2d-d679-4b64-b2a9-03005b21870a",
    "last_edited_time": 1531736996053,
    "parent_id": "300db9dc-27c8-4958-a08b-8d0c37f4cfe5",
    "parent_table": "block",
    "properties": {
      "title": [
        [
          "SumatraPDF 1.9 released"
        ]
      ]
    },
    "type": "page",
    "version": 5,
    "content_resolved": [
      {
        "alive": true,
        "created_by": "bb760e2d-d679-4b64-b2a9-03005b21870a",
        "created_time": 1531736996053,
        "id": "97ebb1ab-bfaa-4913-98a9-af4b830ea526",
        "last_edited_by": "bb760e2d-d679-4b64-b2a9-03005b21870a",
        "last_edited_time": 1531736996053,
        "parent_id": "f1fcdd01-b2dd-4794-a7af-3b00eebda21e",
        "parent_table": "block",
        "properties": {
          "title": [
            [
              "Id: 745001"
            ]
          ]
        },
        "type": "text",
        "version": 1,
        "inline_content": [
          {
            "Text": "Id: 745001"
          }
        ]
      },
      {
        "alive": true,
        "created_by": "bb760e2d-d679-4b64-b2a9-03005b21870a",
        "created_time": 1531736996053,
        "id": "bd8b7b4c-889e-4c57-b73d-c2af98fbbe49",
        "last_edited_by": "bb760e2d-d679-4b64-b2a9-03005b21870a",
        "last_edited_time": 1531736996053,
        "parent_id": "f1fcdd01-b2dd-4794-a7af-3b00eebda21e",
        "parent_table": "block",
        "properties": {
          "title": [
            [
              "Tags: sumatra, releasenotes"
            ]
          ]
        },
        "type": "text",
        "version": 1,
        "inline_content": [
          {
            "Text": "Tags: sumatra, releasenotes"
          }
        ]
      },
      {
        "alive": true,
        "created_by": "bb760e2d-d679-4b64-b2a9-03005b21870a",
        "created_time": 1531736996053,
        "id": "3eab842d-cc91-45d2-b15d-22ef10fc1055",
        "last_edited_by": "bb760e2d-d679-4b64-b2a9-03005b21870a",
        "last_edited_time": 1531736996053,
        "parent_id": "f1fcdd01-b2dd-4794-a7af-3b00eebda21e",
        "parent_table": "block",
        "properties": {
          "title": [
            [
              "Date: 2011-11-24T00:44:29-08:00"
            ]
          ]
        },
        "type": "text",
        "version": 1,
        "inline_content": [
          {
            "Text": "Date: 2011-11-24T00:44:29-08:00"
          }
        ]
      },
      {
        "alive": true,
        "created_by": "bb760e2d-d679-4b64-b2a9-03005b21870a",
        "created_time": 1531736996053,
        "id": "625c28fa-f561-469a-a625-a1fd501645ea",
        "last_edited_by": "bb760e2d-d679-4b64-b2a9-03005b21870a",
        "last_edited_time": 1531736996053,
        "parent_id": "f1fcdd01-b2dd-4794-a7af-3b00eebda21e",
        "parent_table": "block",
        "type": "text",
        "version": 1
      },
      {
        "alive": true,
        "created_by": "bb760e2d-d679-4b64-b2a9-03005b21870a",
        "created_time": 1531736996054,
        "id": "d5b40c05-1d1d-411f-b01b-392542ba6783",
        "last_edited_by": "bb760e2d-d679-4b64-b2a9-03005b21870a",
        "last_edited_time": 1531736996054,
        "parent_id": "f1fcdd01-b2dd-4794-a7af-3b00eebda21e",
        "parent_table": "block",
        "properties": {
          "title": [
            [
              "We",
              [
                [
                  "a",
                  "http://www.ohloh.net/p/4623/contributors"
                ]
              ]
            ],
            [
              " are pleased to announce 1.9 release of "
            ],
            [
              "SumatraPDF",
              [
                [
                  "a",
                  "https://www.sumatrapdfreader.org/free-pdf-reader.html"
                ]
              ]
            ],
            [
              ", a small, fast, free PDF, CHM, DjVu, XPS, CBZ and CBR reader for Windows."
            ]
          ]
        },
        "type": "text",
        "version": 1,
        "inline_content": [
          {
            "Text": "We",
            "Link": "http://www.ohloh.net/p/4623/contributors"
          },
          {
            "Text": " are pleased to announce 1.9 release of "
          },
          {
            "Text": "SumatraPDF",
            "Link": "https://www.sumatrapdfreader.org/free-pdf-reader.html"
          },
          {
            "Text": ", a small, fast, free PDF, CHM, DjVu, XPS, CBZ and CBR reader for Windows."
          }
        ]
      },
      {
        "alive": true,
        "created_by": "bb760e2d-d679-4b64-b2a9-03005b21870a",
        "created_time": 1531736996054,
        "id": "98afe68a-0b3a-4461-8a71-e29baa8c6ddc",
        "last_edited_by": "bb760e2d-d679-4b64-b2a9-03005b21870a",
        "last_edited_time": 1531736996054,
        "parent_id": "f1fcdd01-b2dd-4794-a7af-3b00eebda21e",
        "parent_table": "block",
        "properties": {
          "title": [
            [
              "The most significant addition in this release is support for CHM documents. Sumatra is slowly getting support for more and more document formats."
            ]
          ]
        },
        "type": "text",
        "version": 1,
        "inline_content": [
          {
            "Text": "The most significant addition in this release is support for CHM documents. Sumatra is slowly getting support for more and more document formats."
          }
        ]
      },
      {
        "alive": true,
        "created_by": "bb760e2d-d679-4b64-b2a9-03005b21870a",
        "created_time": 1531736996054,
        "id": "f7e8773f-7326-4401-9319-a36254b3f6a6",
        "last_edited_by": "bb760e2d-d679-4b64-b2a9-03005b21870a",
        "last_edited_time": 1531736996054,
        "parent_id": "f1fcdd01-b2dd-4794-a7af-3b00eebda21e",
        "parent_table": "block",
        "properties": {
          "title": [
            [
              "Robert Prouse contributed support for touch gestures (available on Windows 7 or later, if you have the right hardware i.e. touch-enabled screen)."
            ]
          ]
        },
        "type": "text",
        "version": 1,
        "inline_content": [
          {
            "Text": "Robert Prouse contributed support for touch gestures (available on Windows 7 or later, if you have the right hardware i.e. touch-enabled screen)."
          }
        ]
      },
      {
        "alive": true,
        "created_by": "bb760e2d-d679-4b64-b2a9-03005b21870a",
        "created_time": 1531736996054,
        "id": "807671d0-5d4a-48a3-b0be-af7b98567f28",
        "last_edited_by": "bb760e2d-d679-4b64-b2a9-03005b21870a",
        "last_edited_time": 1531736996054,
        "parent_id": "f1fcdd01-b2dd-4794-a7af-3b00eebda21e",
        "parent_table": "block",
        "properties": {
          "title": [
            [
              "Audio and video files linked from PDF documents are now opened in an external media player."
            ]
          ]
        },
        "type": "text",
        "version": 1,
        "inline_content": [
          {
            "Text": "Audio and video files linked from PDF documents are now opened in an external media player."
          }
        ]
      },
      {
        "alive": true,
        "created_by": "bb760e2d-d679-4b64-b2a9-03005b21870a",
        "created_time": 1531736996054,
        "id": "525f436a-17cf-4740-9dd9-b1c1f53f584b",
        "last_edited_by": "bb760e2d-d679-4b64-b2a9-03005b21870a",
        "last_edited_time": 1531736996054,
        "parent_id": "f1fcdd01-b2dd-4794-a7af-3b00eebda21e",
        "parent_table": "block",
        "properties": {
          "title": [
            [
              "We’ve also improved support for PDF transparency groups."
            ]
          ]
        },
        "type": "text",
        "version": 1,
        "inline_content": [
          {
            "Text": "We’ve also improved support for PDF transparency groups."
          }
        ]
      }
    ],
    "title": "SumatraPDF 1.9 released",
    "format_page": {
      "page_cover": "",
      "page_cover_position": 0,
      "page_font": "",
      "page_full_width": true,
      "page_icon": "",
      "page_small_text": true
    }
  },
  "Users": [
    {
      "email": "kkowalczyk@gmail.com",
      "family_name": "Kowalczyk",
      "given_name": "Krzysztof",
      "id": "bb760e2d-d679-4b64-b2a9-03005b21870a",
      "locale": "en",
      "mobile_onboarding_completed": true,
      "onboarding_completed": true,
      "profile_photo": "https://s3-us-west-2.amazonaws.com/public.notion-static.com/2dcaa66c-7674-4ff6-9924-601785b63561/head-bw-640x960.png",
      "time_zone": "America/Los_Angeles",
      "version": 9
    }
  ],
  "Collections": null,
  "CollectionViews": null
}